README.md
setup.py
exonum_client/__init__.py
exonum_client/api.py
exonum_client/client.py
exonum_client/crypto.py
exonum_client/message.py
exonum_client/module_manager.py
exonum_client/protobuf_loader.py
exonum_client/protoc.py
exonum_client/proofs/__init__.py
exonum_client/proofs/encoder.py
exonum_client/proofs/hasher.py
exonum_client/proofs/utils.py
exonum_client/proofs/list_proof/__init__.py
exonum_client/proofs/list_proof/errors.py
exonum_client/proofs/list_proof/key.py
exonum_client/proofs/list_proof/list_proof.py
exonum_client/proofs/map_proof/__init__.py
exonum_client/proofs/map_proof/branch_node.py
exonum_client/proofs/map_proof/constants.py
exonum_client/proofs/map_proof/errors.py
exonum_client/proofs/map_proof/map_proof.py
exonum_client/proofs/map_proof/map_proof_builder.py
exonum_client/proofs/map_proof/optional_entry.py
exonum_client/proofs/map_proof/proof_path.py
exonum_client/protobuf_provider/__init__.py
exonum_client/protobuf_provider/exonum_api.py
exonum_client/protobuf_provider/filesystem.py
exonum_client/protobuf_provider/github.py
exonum_client/protobuf_provider/provider.py
exonum_python_client.egg-info/PKG-INFO
exonum_python_client.egg-info/SOURCES.txt
exonum_python_client.egg-info/dependency_links.txt
exonum_python_client.egg-info/requires.txt
exonum_python_client.egg-info/top_level.txt