Metadata-Version: 2.1
Name: exonum-python-client
Version: 1.0.1
Summary: Exonum Python Light Client
Home-page: https://github.com/exonum/exonum-python-client
Author: The Exonum Team
Author-email: contact@exonum.com
License: UNKNOWN
Platform: UNKNOWN
Classifier: Programming Language :: Python :: 3
Classifier: License :: OSI Approved :: Apache Software License
Classifier: Operating System :: OS Independent
Classifier: Topic :: Security :: Cryptography
Requires-Python: >=3.4
